jindutiao/__init__.py
jindutiao/setup.py
jindutiao-0.1.0.dist-info/METADATA
jindutiao-0.1.0.dist-info/WHEEL
jindutiao-0.1.0.dist-info/entry_points.txt
jindutiao-0.1.0.dist-info/top_level.txt
jindutiao-0.1.0.dist-info/RECORD
