Metadata-Version: 2.1
Name: jindutiao
Version: 0.1.0
Summary: 进度条ProgressBar
Home-page: https://github.com/theCoder-WM
Author: William Ma
Author-email: 3327821469@qq.com
License: UNKNOWN
Platform: UNKNOWN
